{
  "version": 2,
  "levels": {
    "institution": [
      {
        "id": "identity",
        "title": "Identity & description",
        "order": 1,
        "required": true,
        "widget": "prose",
        "fields": [
          "description_text",
          "student_body_size",
          "campus_photo",
          "website_url",
          "type",
          "campus_setting",
          "founded_year",
          "social_links"
        ]
      },
      {
        "id": "rankings",
        "title": "Rankings & classification",
        "order": 2,
        "required": true,
        "widget": "chip-list",
        "fields": [
          "qs",
          "the",
          "usnews",
          "carnegie",
          "accreditor"
        ]
      },
      {
        "id": "report_card",
        "title": "Report-card key stats",
        "order": 3,
        "required": true,
        "widget": "stat-grid",
        "fields": [
          "admit_rate",
          "avg_net_price",
          "earnings_10yr",
          "grad_rate",
          "retention",
          "completion_4yr"
        ]
      },
      {
        "id": "admissions_funnel",
        "title": "Admissions funnel",
        "order": 4,
        "required": true,
        "widget": "stat-grid",
        "fields": [
          "applicants",
          "admits",
          "cycle",
          "test_scores"
        ]
      },
      {
        "id": "diversity",
        "title": "Diversity",
        "order": 5,
        "required": true,
        "widget": "stat-grid",
        "fields": [
          "demographics"
        ]
      },
      {
        "id": "recognition",
        "title": "Recognition",
        "order": 6,
        "required": false,
        "widget": "chip-list",
        "fields": [
          "nobel",
          "macarthur",
          "medal_science"
        ]
      },
      {
        "id": "scale",
        "title": "By the numbers",
        "order": 7,
        "required": true,
        "widget": "stat-grid",
        "fields": [
          "faculty_count",
          "sf_ratio",
          "research_centers",
          "endowment"
        ]
      },
      {
        "id": "outcomes",
        "title": "Outcomes",
        "order": 8,
        "required": true,
        "widget": "stat-grid",
        "fields": [
          "placement",
          "industries"
        ]
      },
      {
        "id": "cost_aid",
        "title": "Cost & aid",
        "order": 9,
        "required": true,
        "widget": "stat-grid",
        "fields": [
          "coa",
          "pell",
          "loan",
          "median_debt"
        ]
      },
      {
        "id": "location",
        "title": "Location & campus basics",
        "order": 10,
        "required": true,
        "widget": "none",
        "fields": [
          "lat",
          "lng",
          "campus_location"
        ]
      },
      {
        "id": "campus_resources",
        "title": "Campus resources",
        "order": 11,
        "required": true,
        "widget": "chip-list",
        "fields": [
          "research",
          "campus_life"
        ]
      },
      {
        "id": "feeds",
        "title": "Events & updates feeds",
        "order": 12,
        "required": false,
        "widget": "none",
        "fields": [
          "content_sources"
        ]
      },
      {
        "id": "citation",
        "title": "Sources",
        "order": 13,
        "required": true,
        "widget": "citation-block",
        "fields": [
          "sources"
        ]
      }
    ],
    "school": [
      {
        "id": "identity",
        "title": "Identity",
        "order": 1,
        "required": true,
        "widget": "prose",
        "fields": [
          "name",
          "description",
          "website_url"
        ]
      },
      {
        "id": "about_detail",
        "title": "About \u2014 facts, leadership, faculty",
        "order": 2,
        "required": true,
        "widget": "stat-grid",
        "fields": [
          "founded",
          "leadership",
          "faculty",
          "research_centers",
          "named_for",
          "source"
        ]
      },
      {
        "id": "quick_facts",
        "title": "Quick facts (inherited from institution)",
        "order": 3,
        "required": false,
        "widget": "none",
        "fields": [
          "admit_rate",
          "grad_rate",
          "students"
        ]
      },
      {
        "id": "feeds",
        "title": "Events & updates feeds",
        "order": 4,
        "required": false,
        "widget": "none",
        "fields": [
          "content_sources"
        ]
      }
    ],
    "program": [
      {
        "id": "basics",
        "title": "Basic info",
        "order": 1,
        "required": true,
        "widget": "stat-grid",
        "fields": [
          "program_name",
          "degree_type",
          "duration_months",
          "delivery_format",
          "description_text",
          "website_url",
          "department",
          "highlights",
          "who_its_for"
        ]
      },
      {
        "id": "tracks",
        "title": "Curriculum & structure",
        "order": 2,
        "required": true,
        "widget": "stat-grid",
        "fields": [
          "tracks"
        ]
      },
      {
        "id": "admissions",
        "title": "Admissions",
        "order": 3,
        "required": true,
        "widget": "stat-grid",
        "fields": [
          "materials",
          "deadlines",
          "recommendations",
          "international",
          "application_fee",
          "req_source"
        ]
      },
      {
        "id": "costs",
        "title": "Costs & aid",
        "order": 4,
        "required": true,
        "widget": "stat-grid",
        "fields": [
          "tuition",
          "total_coa",
          "breakdown",
          "cost_source"
        ]
      },
      {
        "id": "outcomes",
        "title": "Outcomes",
        "order": 5,
        "required": true,
        "widget": "distribution",
        "fields": [
          "employment_rate",
          "median_salary",
          "salary_25th",
          "salary_75th",
          "mean_salary",
          "signing_bonus",
          "top_industries",
          "top_employers",
          "class_size",
          "conditions",
          "outcomes_source",
          "outcomes_source_url"
        ]
      },
      {
        "id": "insights",
        "title": "Insights \u2014 class profile, faculty, reviews",
        "order": 6,
        "required": true,
        "widget": "stat-grid",
        "fields": [
          "class_profile",
          "class_intl",
          "class_source",
          "faculty",
          "faculty_dir",
          "reviews",
          "reviews_themes",
          "reviews_sources"
        ]
      },
      {
        "id": "feeds",
        "title": "Events & updates feeds",
        "order": 7,
        "required": true,
        "widget": "none",
        "fields": [
          "content_sources"
        ]
      }
    ]
  }
}
